endoflife_lib-0.1.2.dist-info/licenses/LICENSE
eoltracker/__init__.py
eoltracker/api.py
eoltracker/exceptions.py
endoflife_lib-0.1.2.dist-info/METADATA
endoflife_lib-0.1.2.dist-info/WHEEL
endoflife_lib-0.1.2.dist-info/top_level.txt
endoflife_lib-0.1.2.dist-info/RECORD
