Metadata-Version: 2.4
Name: endoflife-lib
Version: 0.1.2
Summary: A client for fetching end-of-life and product data from endoflife.date
Author-email: Joshua Shen <joshshen2012@gmail.com>
License: MIT
Project-URL: Homepage, https://github.com/joshsh02/endoflife-lib
Requires-Python: >=3.7
License-File: LICENSE
Requires-Dist: aiohttp>=3.8.0
Dynamic: license-file
